tapioca_vindi/__init__.py
tapioca_vindi/resource_mapping.py
tapioca_vindi/tapioca_vindi.py
tapioca_vindi-1.0.2.dist-info/LICENSE
tapioca_vindi-1.0.2.dist-info/METADATA
tapioca_vindi-1.0.2.dist-info/WHEEL
tapioca_vindi-1.0.2.dist-info/top_level.txt
tapioca_vindi-1.0.2.dist-info/RECORD
